auto_ninja/__init__.py
auto_ninja/cases.py
auto_ninja/django_services.py
auto_ninja/main.py
auto_ninja/services.py
auto_ninja/templates/endpoint.py.txt
auto_ninja/templates/endpoint_init.py.txt
auto_ninja/templates/main.py.txt
auto_ninja/templates/schema.py.txt
auto_ninja/templates/schema_init.py.txt
auto_ninja/templates/services.py.txt
auto_ninja/templates/utils.py.txt
auto_ninja-1.0.2.dist-info/LICENSE.md
auto_ninja-1.0.2.dist-info/METADATA
auto_ninja-1.0.2.dist-info/WHEEL
auto_ninja-1.0.2.dist-info/entry_points.txt
auto_ninja-1.0.2.dist-info/RECORD
