Metadata-Version: 2.1
Name: auto-ninja
Version: 1.0.2
Summary: A lightweight library to quickly build CRUD API endpoints for Django Ninja.
Home-page: https://github.com/fa-krug/auto-ninja
License: MIT
Keywords: django,ninja,crud,auto
Author: Sascha Krug
Requires-Python: >=3.10,<4.0
Classifier: Development Status :: 5 - Production/Stable
Classifier: Environment :: Web Environment
Classifier: Framework :: Django
Classifier: Framework :: Django :: 4.0
Classifier: Framework :: Django :: 4.1
Classifier: Framework :: Django :: 4.2
Classifier: Framework :: Django :: 5.0
Classifier: Framework :: Django :: 5.1
Classifier: License :: OSI Approved :: MIT License
Classifier: Operating System :: OS Independent
Classifier: Programming Language :: Python :: 3
Classifier: Programming Language :: Python :: 3.10
Classifier: Programming Language :: Python :: 3.11
Classifier: Programming Language :: Python :: 3.12
Classifier: Programming Language :: Python :: 3.13
Requires-Dist: typer (>=0.15.0,<0.16.0)
Project-URL: Repository, https://github.com/fa-krug/auto-ninja
